{
    "Ar36": {
        "error": 0.00039023684287765355, 
        "fit": "linear", 
        "value": 0.016914475814241582
    }, 
    "Ar37": {
        "error": 0.025692969648416136, 
        "fit": "linear", 
        "value": 7.5082554825135741
    }, 
    "Ar38": {
        "error": 0.047128964792056985, 
        "fit": "linear", 
        "value": 35.042762428192304
    }, 
    "Ar39": {
        "error": 0.25835020766226763, 
        "fit": "linear", 
        "value": 2805.4440367877301
    }, 
    "Ar40": {
        "error": 0.13286740357448015, 
        "fit": "linear", 
        "value": 2969.080624672657
    }, 
    "Ar41": {
        "error": 0.01095820027049927, 
        "fit": "average", 
        "value": 0.29355385847079257
    }
}