{
    "Ar36": {
        "error": 0.00026165713795960223, 
        "fit": "linear", 
        "value": 0.0072562676603515029
    }, 
    "Ar37": {
        "error": 0.024727022097169246, 
        "fit": "linear", 
        "value": 3.8394580129860785
    }, 
    "Ar38": {
        "error": 0.044616045872748644, 
        "fit": "linear", 
        "value": 18.108795937587018
    }, 
    "Ar39": {
        "error": 0.16499664517361196, 
        "fit": "linear", 
        "value": 1452.914604165197
    }, 
    "Ar40": {
        "error": 0.085838730798454874, 
        "fit": "linear", 
        "value": 1539.9543135137669
    }, 
    "Ar41": {
        "error": 0.010523406801794175, 
        "fit": "average", 
        "value": -0.0092623199697118245
    }
}