{
    "AX": {
        "error": 0.05435366807887912, 
        "fit": "average_SEM", 
        "value": -0.011188690414807448
    }, 
    "CDD": {
        "error": 2.799499994932217e-05, 
        "fit": "average_SEM", 
        "value": 5.169579526409507e-06
    }, 
    "H1": {
        "error": 0.14087401866075983, 
        "fit": "average_SEM", 
        "value": 0.020040231201952943
    }, 
    "H2": {
        "error": 0.10934175605167148, 
        "fit": "average_SEM", 
        "value": -0.34662663042545316
    }, 
    "L1": {
        "error": 0.14939171360022108, 
        "fit": "average_SEM", 
        "value": -0.10045001437214927
    }, 
    "L2": {
        "error": 0.13151566412829235, 
        "fit": "average_SEM", 
        "value": -0.0265284858008575
    }
}