{
    "AX": {
        "error": 0.06676701718699572, 
        "fit": "average_SEM", 
        "value": -0.013832715025950569
    }, 
    "CDD": {
        "error": 4.690210717941012e-05, 
        "fit": "average_SEM", 
        "value": 1.5546937356702982e-05
    }, 
    "H1": {
        "error": 0.12629639064788978, 
        "fit": "average_SEM", 
        "value": 0.026852522213206005
    }, 
    "H2": {
        "error": 0.14669209369985153, 
        "fit": "average_SEM", 
        "value": -0.30380284670326446
    }, 
    "L1": {
        "error": 0.145375367503506, 
        "fit": "average_SEM", 
        "value": -0.1080305937742297
    }, 
    "L2": {
        "error": 0.1265679317677023, 
        "fit": "average_SEM", 
        "value": -0.013312284839856955
    }
}