{
    "CDD": {
        "error": 2.802462017628634e-05, 
        "fit": "average_SEM", 
        "value": 5.182312452234328e-06
    }, 
    "H1": {
        "error": 0.13555305540274276, 
        "fit": "average_SEM", 
        "value": 0.038937040276262755
    }, 
    "H2": {
        "error": 0.12870866882475923, 
        "fit": "average_SEM", 
        "value": -0.03864268772789122
    }, 
    "L1": {
        "error": 0.1425234910075259, 
        "fit": "average_SEM", 
        "value": -0.08216454496141523
    }, 
    "L2": {
        "error": 0.14447899376289755, 
        "fit": "average_SEM", 
        "value": -0.010219375563307646
    }
}