{
    "AX": {
        "error": 0.5444619593123493, 
        "fit": "average", 
        "value": -0.6424687903568459
    }, 
    "CDD": {
        "error": 1.7057202553073167e-05, 
        "fit": "average", 
        "value": 0.0001595863684390982
    }, 
    "H1": {
        "error": 0.012126619161910508, 
        "fit": "average", 
        "value": 0.061688043041956714
    }, 
    "H2": {
        "error": 0.013723827696398523, 
        "fit": "average", 
        "value": 0.22212341400898164
    }, 
    "L1": {
        "error": 0.02290521230847988, 
        "fit": "average", 
        "value": -0.16669600045618913
    }, 
    "L2": {
        "error": 0.014125149511534233, 
        "fit": "average", 
        "value": 0.04181634563331803
    }
}