{
    "Ar36": {
        "error": 0.00040048925152671121, 
        "fit": "linear", 
        "value": 0.026117933090609287
    }, 
    "Ar37": {
        "error": 0.02746402351112744, 
        "fit": "linear", 
        "value": 9.5178753957181854
    }, 
    "Ar38": {
        "error": 0.029960444386792233, 
        "fit": "linear", 
        "value": 27.394945229931828
    }, 
    "Ar39": {
        "error": 0.21992669828445657, 
        "fit": "linear", 
        "value": 2206.7161914435046
    }, 
    "Ar40": {
        "error": 0.12306150559023524, 
        "fit": "linear", 
        "value": 2346.7782113444582
    }, 
    "Ar41": {
        "error": 0.010386718697366132, 
        "fit": "average", 
        "value": 0.0029133691654230159
    }
}