{
    "Ar36": {
        "error": 0.00025526857174573958, 
        "fit": "linear", 
        "value": 0.0061718294584982882
    }, 
    "Ar37": {
        "error": 0.024208457380185192, 
        "fit": "linear", 
        "value": 2.6744647636107972
    }, 
    "Ar38": {
        "error": 0.038450556595021196, 
        "fit": "linear", 
        "value": 12.039719791235125
    }, 
    "Ar39": {
        "error": 0.11906926132826021, 
        "fit": "linear", 
        "value": 963.81560183193972
    }, 
    "Ar40": {
        "error": 0.074004746980619915, 
        "fit": "linear", 
        "value": 1030.0267933369726
    }, 
    "Ar41": {
        "error": 0.010143573211100012, 
        "fit": "average", 
        "value": 0.22750559876672924
    }
}