{
    "Ar36": {
        "error": 0.00089707082023823327, 
        "fit": "parabolic", 
        "value": 0.0028905465027142356
    }, 
    "Ar37": {
        "error": 0.14479259521240637, 
        "fit": "linear", 
        "value": -0.023846236761257321
    }, 
    "Ar38": {
        "error": 0.14793453256543632, 
        "fit": "linear", 
        "value": -0.12743804095674663
    }, 
    "Ar39": {
        "error": 0.069781445148476687, 
        "fit": "parabolic", 
        "value": 1.6118142236611417
    }, 
    "Ar40": {
        "error": 0.12654522793109044, 
        "fit": "parabolic", 
        "value": 2.5075113087687013
    }, 
    "Ar41": {
        "error": 0.1249128461545147, 
        "fit": "average_SEM", 
        "value": -0.334392395898855
    }
}