{
    "Ar36": {
        "error": 0.00087823369372313099, 
        "fit": "parabolic", 
        "value": 0.0027503253351651613
    }, 
    "Ar37": {
        "error": 0.13212420240347081, 
        "fit": "linear", 
        "value": 0.0011689413288630997
    }, 
    "Ar38": {
        "error": 0.14469570016124816, 
        "fit": "linear", 
        "value": 0.49024616336043858
    }, 
    "Ar39": {
        "error": 0.078069007388933589, 
        "fit": "parabolic", 
        "value": 45.713271296729644
    }, 
    "Ar40": {
        "error": 0.16608926629256271, 
        "fit": "parabolic", 
        "value": 48.851052584154559
    }, 
    "Ar41": {
        "error": 0.12070925178827543, 
        "fit": "average_SEM", 
        "value": -0.061058554492774419
    }
}