{
    "Ar36": {
        "error": 0.0011137733084614027, 
        "fit": "parabolic", 
        "value": 0.0059575892822637758
    }, 
    "Ar37": {
        "error": 0.12048488022779816, 
        "fit": "linear", 
        "value": 0.065012105829773389
    }, 
    "Ar38": {
        "error": 0.15918069944508673, 
        "fit": "linear", 
        "value": 1.758579222380098
    }, 
    "Ar39": {
        "error": 0.11230418713703941, 
        "fit": "parabolic", 
        "value": 146.6354377932355
    }, 
    "Ar40": {
        "error": 0.20711024835990605, 
        "fit": "parabolic", 
        "value": 155.88837142227311
    }, 
    "Ar41": {
        "error": 0.12846226578483153, 
        "fit": "average_SEM", 
        "value": -0.030508515422762787
    }
}