{
    "AX": {
        "error": 0.05694635936030798, 
        "fit": "average_SEM", 
        "value": -0.013536034116340388
    }, 
    "CDD": {
        "error": 3.5711372458756305e-05, 
        "fit": "average_SEM", 
        "value": 8.637187420390546e-06
    }, 
    "H1": {
        "error": 0.1343443508373546, 
        "fit": "average_SEM", 
        "value": 0.0594457021277372
    }, 
    "H2": {
        "error": 0.12891322146027537, 
        "fit": "average_SEM", 
        "value": -0.2899925211237537
    }, 
    "L1": {
        "error": 0.1474780448768926, 
        "fit": "average_SEM", 
        "value": -0.09049187270215447
    }, 
    "L2": {
        "error": 0.14787976093221086, 
        "fit": "average_SEM", 
        "value": 0.035468433803988675
    }
}