{
    "Ar36": {
        "error": 0.00019572823366924755, 
        "fit": "parabolic", 
        "value": 0.003874508169629946
    }, 
    "Ar37": {
        "error": 0.013624184936614608, 
        "fit": "linear", 
        "value": 0.057790486888408155
    }, 
    "Ar38": {
        "error": 0.024706221581788163, 
        "fit": "linear", 
        "value": -0.21511764130555455
    }, 
    "Ar39": {
        "error": 0.020118871970634635, 
        "fit": "parabolic", 
        "value": -0.0025899248204905197
    }, 
    "Ar40": {
        "error": 0.024147555760998078, 
        "fit": "parabolic", 
        "value": 1.0862382174398284
    }, 
    "Ar41": {
        "error": 0.0064089327409034003, 
        "fit": "average", 
        "value": 0.20860827332449844
    }
}