{
    "CDD": {
        "error": 2.8024620176286337e-05, 
        "fit": "average_SEM", 
        "value": 5.182312452234328e-06
    }, 
    "H1": {
        "error": 0.1456300782649364, 
        "fit": "average_SEM", 
        "value": 0.016867448761089084
    }, 
    "H2": {
        "error": 0.14783335092583544, 
        "fit": "average_SEM", 
        "value": -0.32723300530730437
    }, 
    "L1": {
        "error": 0.13050594334283613, 
        "fit": "average_SEM", 
        "value": -0.1194736196892336
    }, 
    "L2": {
        "error": 0.13754251925892083, 
        "fit": "average_SEM", 
        "value": -0.04122255677745367
    }
}